us/__init__.py
us/states.py
us/unitedstatesofamerica.py
us/cli/__init__.py
us/cli/states.py
us/tests/__init__.py
us/tests/conftest.py
us/tests/test_timezones.py
us/tests/test_us.py
us_aidentified-3.0.2.dist-info/LICENSE
us_aidentified-3.0.2.dist-info/METADATA
us_aidentified-3.0.2.dist-info/WHEEL
us_aidentified-3.0.2.dist-info/entry_points.txt
us_aidentified-3.0.2.dist-info/top_level.txt
us_aidentified-3.0.2.dist-info/RECORD
