Metadata-Version: 2.1
Name: us-aidentified
Version: 3.0.2
Summary: US state meta information and other fun stuff
Home-page: https://github.com/dgilmanAIDENTIFIED/python-us
Author: Jeremy Carbaugh
Author-email: jeremy@jcarbaugh.com
License: BSD
Platform: any
Classifier: Programming Language :: Python :: 3.6
Classifier: Programming Language :: Python :: 3.7
Classifier: Programming Language :: Python :: 3.8
Classifier: Programming Language :: Python :: 3.9
Classifier: Programming Language :: Python :: 3.10
License-File: LICENSE
Requires-Dist: jellyfish (<1.0)
